toydl/__init__.py
toydl/core/__init__.py
toydl/core/module.py
toydl/core/operator.py
toydl/core/optim/__init__.py
toydl/core/optim/_base.py
toydl/core/optim/_momentum.py
toydl/core/optim/_sgd.py
toydl/core/scalar/__init__.py
toydl/core/scalar/bp.py
toydl/core/scalar/context.py
toydl/core/scalar/history.py
toydl/core/scalar/scalar.py
toydl/dataset/__init__.py
toydl/dataset/base.py
toydl/dataset/exception.py
toydl/dataset/simple.py
toydl/dataset/simulation.py
toydl/layer/__init__.py
toydl/layer/linear.py
toydl/loss/__init__.py
toydl/loss/base.py
toydl/loss/cross_entropy.py
toydl/network/__init__.py
toydl/network/mlp.py
toydl-0.3.0.dist-info/METADATA
toydl-0.3.0.dist-info/WHEEL
toydl-0.3.0.dist-info/licenses/LICENSE
toydl-0.3.0.dist-info/RECORD
