Metadata-Version: 2.4
Name: toydl
Version: 0.3.0
Summary: ToyDL: Deep Learning from Scratch
Project-URL: Homepage, https://shenxiangzhuang.github.io/toydl
Project-URL: Repository, https://github.com/shenxiangzhuang/toydl
Author-email: Xiangzhuang Shen <datahonor@gmail.com>
License-Expression: MIT
License-File: LICENSE
Keywords: engineering,machine learning,statistics
Classifier: Development Status :: 5 - Production/Stable
Classifier: Intended Audience :: Developers
Classifier: Intended Audience :: Science/Research
Classifier: License :: OSI Approved :: MIT License
Classifier: Operating System :: OS Independent
Classifier: Programming Language :: Python :: 3.12
Classifier: Programming Language :: Python :: 3.13
Classifier: Topic :: Scientific/Engineering
Classifier: Topic :: Scientific/Engineering :: Mathematics
Requires-Python: <4.0,>=3.12
Requires-Dist: matplotlib<4,>=3.8.2
Provides-Extra: dev
Requires-Dist: ipython<9,>=8.7.0; extra == 'dev'
Requires-Dist: marimo>=0.14.13; extra == 'dev'
Requires-Dist: mypy<0.982,>=0.981; extra == 'dev'
Requires-Dist: pre-commit<4,>=3.5.0; extra == 'dev'
Requires-Dist: pydeps<2,>=1.12.17; extra == 'dev'
Requires-Dist: ruff>=0.12.5; extra == 'dev'
Requires-Dist: tqdm<5,>=4.0.0; extra == 'dev'
Requires-Dist: ty>=0.0.1a16; extra == 'dev'
Provides-Extra: docs
Requires-Dist: mkdocs; extra == 'docs'
Requires-Dist: mkdocs-autorefs; extra == 'docs'
Requires-Dist: mkdocs-bibtex; extra == 'docs'
Requires-Dist: mkdocs-git-committers-plugin-2; extra == 'docs'
Requires-Dist: mkdocs-git-revision-date-localized-plugin; extra == 'docs'
Requires-Dist: mkdocs-material; extra == 'docs'
Requires-Dist: mkdocs-material-extensions; extra == 'docs'
Requires-Dist: mkdocstrings; extra == 'docs'
Requires-Dist: mkdocstrings-python; extra == 'docs'
Provides-Extra: test
Requires-Dist: hypothesis<7,>=6.61.0; extra == 'test'
Requires-Dist: pytest-cov<5,>=4.0.0; extra == 'test'
Requires-Dist: pytest-sugar<0.10,>=0.9.7; extra == 'test'
Requires-Dist: pytest<8,>=7.1.3; extra == 'test'
